{
  "providers": {
    "awscloudformation": {
      "AuthRoleName": "amplify-equipmentapi-dev-01537-authRole",
      "UnauthRoleArn": "arn:aws:iam::328587249661:role/amplify-equipmentapi-dev-01537-unauthRole",
      "AuthRoleArn": "arn:aws:iam::328587249661:role/amplify-equipmentapi-dev-01537-authRole",
      "Region": "us-west-1",
      "DeploymentBucketName": "amplify-equipmentapi-dev-01537-deployment",
      "UnauthRoleName": "amplify-equipmentapi-dev-01537-unauthRole",
      "StackName": "amplify-equipmentapi-dev-01537",
      "StackId": "arn:aws:cloudformation:us-west-1:328587249661:stack/amplify-equipmentapi-dev-01537/34372850-5411-11ec-90b8-0215fde01e6f",
      "AmplifyAppId": "dorvzu4bsg4r3"
    }
  },
  "function": {
    "sensorlambdav3": {
      "build": true,
      "providerPlugin": "awscloudformation",
      "service": "Lambda",
      "lastBuildTimeStamp": "2021-12-03T09:27:08.412Z",
      "lastBuildType": "DEV",
      "lastPackageTimeStamp": "2021-12-03T09:27:18.156Z",
      "distZipFilename": "sensorlambdav3-77376657314353387571-build.zip",
      "s3Bucket": {
        "deploymentBucketName": "amplify-equipmentapi-dev-01537-deployment",
        "s3Key": "amplify-builds/sensorlambdav3-77376657314353387571-build.zip"
      },
      "providerMetadata": {
        "s3TemplateURL": "https://s3.amazonaws.com/amplify-equipmentapi-dev-01537-deployment/amplify-cfn-templates/function/sensorlambdav3-cloudformation-template.json",
        "logicalId": "functionsensorlambdav3"
      },
      "lastPushTimeStamp": "2021-12-03T09:28:27.407Z",
      "output": {
        "Region": "us-west-1",
        "Arn": "arn:aws:lambda:us-west-1:328587249661:function:sensorlambdav3-dev",
        "Name": "sensorlambdav3-dev",
        "LambdaExecutionRole": "equipmentapiLambdaRole1f56f018-dev"
      },
      "lastPushDirHash": "wGF129cfUPXjRCKHGZ+u+bPsL9M=",
      "lastDevBuildTimeStamp": "2021-12-03T09:33:06.894Z"
    }
  },
  "api": {
    "equipmentapi": {
      "service": "API Gateway",
      "providerPlugin": "awscloudformation",
      "dependsOn": [
        {
          "category": "function",
          "resourceName": "sensorlambdav3",
          "attributes": [
            "Name",
            "Arn"
          ]
        }
      ],
      "providerMetadata": {
        "s3TemplateURL": "https://s3.amazonaws.com/amplify-equipmentapi-dev-01537-deployment/amplify-cfn-templates/api/equipmentapi-cloudformation-template.json",
        "logicalId": "apiequipmentapi"
      },
      "lastPushTimeStamp": "2021-12-03T09:28:27.378Z",
      "output": {
        "ApiName": "equipmentapi",
        "RootUrl": "https://cvsg7g3cud.execute-api.us-west-1.amazonaws.com/dev",
        "ApiId": "cvsg7g3cud"
      },
      "lastPushDirHash": "pJIq3pozfE1haGirU4a5fmQQLLw="
    }
  }
}